MicroscoPy-0.9.dist-info/DESCRIPTION.rst
MicroscoPy-0.9.dist-info/METADATA
MicroscoPy-0.9.dist-info/RECORD
MicroscoPy-0.9.dist-info/WHEEL
MicroscoPy-0.9.dist-info/metadata.json
MicroscoPy-0.9.dist-info/top_level.txt
microscopy/__init__.py
microscopy/display.py
microscopy/hal.py
microscopy/keypad.py
microscopy/scan.py
microscopy/device_adapters/__init__.py
microscopy/device_adapters/actuators.py
microscopy/device_adapters/hybrids.py
microscopy/device_adapters/sensors.py
microscopy/utilities/__init__.py
microscopy/utilities/andorgui.py
microscopy/utilities/camdisp.py
microscopy/utilities/interruptable_region.py
microscopy/utilities/logging.py
microscopy/utilities/misc.py
microscopy/utilities/plotting.py
microscopy/utilities/pxlflygui.py
microscopy/utilities/setup-thermistor.py
microscopy/utilities/terminal.py
microscopy/utilities/waveform/__init__.py
microscopy/utilities/waveform/waveform-setup.py
microscopy/utilities/waveform/waveform.py
