Metadata-Version: 2.0
Name: MicroscoPy
Version: 0.9
Summary: Simple platform for scanning confocal microscopy and spectroscopy
Home-page: UNKNOWN
Author: Guillaume Lepert
Author-email: guillaume.lepert07@imperial.ac.uk
License: UNKNOWN
Platform: UNKNOWN
Classifier: Development Status :: 5 - Production/Stable
Classifier: Environment :: Console
Classifier: Intended Audience :: Science/Research
Classifier: License :: OSI Approved :: MIT License
Classifier: Natural Language :: English
Classifier: Operating System :: POSIX :: Linux
Classifier: Programming Language :: Python :: 2.7
Classifier: Topic :: Scientific/Engineering
Requires-Dist: cycler
Requires-Dist: h5py
Requires-Dist: matplotlib
Requires-Dist: numpy
